setup.cfg
setup.py
gpolyline/__init__.py
gpolyline/glineenc.py
gpolyline.egg-info/PKG-INFO
gpolyline.egg-info/SOURCES.txt
gpolyline.egg-info/dependency_links.txt
gpolyline.egg-info/top_level.txt