Metadata-Version: 1.1
Name: gpolyline
Version: 0.0.2
Summary: Converts a series of latitude/longitude points to an encoded string for use with Google Maps
Home-page: http://github.com/rcmachado/gpolyline
Author: Rodrigo Machado
Author-email: rcmachado@gmail.com
License: OSI
Keywords: googlemaps
Platform: UNKNOWN
Classifier: Development Status :: 3 - Alpha
Classifier: Intended Audience :: Developers
Classifier: License :: OSI Approved
Classifier: Natural Language :: English
Classifier: Operating System :: POSIX :: Linux
Classifier: Programming Language :: Python :: 2.6
Classifier: Topic :: Software Development :: Libraries :: Application Frameworks
